pyfoster/__init__.py
pyfoster/custom_logger.py
pyfoster-0.1.1.dist-info/WHEEL
pyfoster-0.1.1.dist-info/METADATA
pyfoster-0.1.1.dist-info/RECORD
