Metadata-Version: 2.1
Name: pyfoster
Version: 0.1.1
Summary: Python Utility Functions on Steroid
License: MIT
Author: rednafi
Author-email: redowan.nafi@gmail.com
Requires-Python: >=3.7,<4.0
Classifier: License :: OSI Approved :: MIT License
Classifier: Programming Language :: Python :: 3
Classifier: Programming Language :: Python :: 3.7
